Workbook

Sheet Accounts (wide)
I1: CUMULATIVE REVENUES | L1: OPENING BALANCE | P1: NON-REGULAR PAYMENTS | S1: CURRENT YEAR REVENUES | V1: EXPENDITURES
A2: Register | B2: Waqf | C2: Location | D2: Account interval (raw Hijri) | E2: Start (CE) | F2: End (CE) | G2: Currency | H2: Account type | I2: Cumulative revenues (L1) | J2: of which received (L1A) | K2: of which receivable (L1B) | L2: Opening balance, total (L2) | M2: Opening cash (L2A) | N2: Opening receivable (L2B) | O2: Prior receivable collected (L2T) | P2: Loan, (L3.1) | Q2: Advance payment (L3.2) | R2: Other inflow (L3.3) | S2: Current-year revenue, total (L4) | T2: of which received (L4A) | U2: of which accrued (L4B) | V2: Expenditure, total (L5) | W2: Salaries (L5A) | X2: Outlays & repair (L5B) | Y2: Balance after expenditure (L6) | Z2: Non-expenditure payments (L7) | AA2: Closing balance,(L8) | AB2: Cumulative receivables(L9) | AC2: Closing net of receivables (L10) | AD2: Empoyee N (L11) | AE2: Daily wage total (L12)
A3: MAD.d 1703_p102 | B3: Canfeda Hatun | C3: Istanbul | D3: gurre-yi Muharrem sene 1024 ila gayet-i Zilhicce sene-yi minhü | E3: 1615 | F3: 1616 | G3: Akçe | H3: certified final account | I3: 345973 | J3: 345973 | K3: 0 | L3: 1313 | M3: 1313 | N3: 0 | O3: 0 | P3: 0 | Q3: 0 | R3: 0 | S3: 344660 | T3: 344660 | U3: 0 | V3: 254791 | W3: 103560 | X3: 151231 | Y3: 91182 | Z3: 86080 | AA3: 5102 | AB3: 0 | AC3: 5102 | AD3: 75 | AE3: 286
A4: MAD.d 1703_p99 | B4: Canfeda Hatun | C4: Istanbul | D4: gurre-yi Muharrem sene 1025 ila gayet-i Zilhicce sene-yi minhü | E4: 1616 | F4: 1617 | G4: Akçe | H4: certified final account | I4: 208122 | J4: 208122 | K4: 0 | L4: 5102 | M4: 5102 | N4: 0 | O4: 0 | P4: 0 | Q4: 0 | R4: 0 | S4: 203020 | T4: 203020 | U4: 0 | V4: 206705 | W4: 105000 | X4: 101705 | Y4: 1417 | Z4: 0 | AA4: 1417 | AB4: 0 | AC4: 1417 | AD4: 79 | AE4: 291
A5: MAD.d 1703_p95 | B5: Canfeda Hatun | C5: Istanbul | D5: gurre-yi Muharrem sene 1026 ila gayet-i Zilhicce | E5: 1617 | F5: 1617 | G5: Akçe | H5: certified final account | I5: 189962 | J5: 187962 | K5: 2000 | L5: 1417 | M5: 1417 | N5: 0 | O5: 0 | P5: 0 | Q5: 0 | R5: 0 | S5: 188545 | T5: 186545 | U5: 2000 | V5: 184954 | W5: 105000 | X5: 79954 | Y5: 5008 | Z5: 0 | AA5: 5008 | AB5: 2000 | AC5: 3008 | AD5: 79 | AE5: 291
A6: MAD.d 1703_p92 | B6: Canfeda Hatun | C6: Istanbul | D6: gurre-yi Muharrem sene 1027 ila gayet-i Zilhicce | E6: 1617 | F6: 1618 | G6: Akçe | H6: certified final account | I6: 201548 | J6: 197548 | K6: 4000 | L6: 5008 | M6: 3008 | N6: 2000 | O6: 0 | P6: 0 | Q6: 0 | R6: 0 | S6: 196540 | T6: 194540 | U6: 2000 | V6: 197448 | W6: 106800 | X6: 90648 | Y6: 4100 | Z6: 0 | AA6: 4100 | AB6: 4000 | AC6: 100 | AD6: 78 | AE6: 283
A7: MAD.d 1703_p88 | B7: Canfeda Hatun | C7: Istanbul | D7: gurre-yi Muharrem sene 1028 ila gayet-i Zilhicce | E7: 1618 | F7: 1619 | G7: Akçe | H7: certified final account | I7: 217205 | J7: 211205 | K7: 6000 | L7: 4100 | M7: 100 | N7: 4000 | O7: 0 | P7: 0 | Q7: 0 | R7: 0 | S7: 213105 | T7: 211105 | U7: 2000 | V7: 198825 | W7: 107160 | X7: 91665 | Y7: 14280 | Z7: 0 | AA7: 14280 | AB7: 6000 | AC7: 8280 | AD7: 79 | AE7: 297
A8: MAD.d 1703_p85 | B8: Canfeda Hatun | C8: Istanbul | D8: gurre-yi Muharrem sene 1029 ila gayet-i sene-yi minhü | E8: 1619 | F8: 1620 | G8: Akçe | H8: certified final account | I8: 243740 | J8: 234960 | K8: 8780 | L8: 14280 | M8: 8280 | N8: 6000 | O8: 0 | P8: 0 | Q8: 0 | R8: 0 | S8: 229460 | T8: 226680 | U8: 2780 | V8: 219140 | W8: 107180 | X8: 111960 | Y8: 24600 | Z8: 0 | AA8: 24600 | AB8: 8780 | AC8: 15820 | AD8: 80 | AE8: 297
A9: MAD.d 1703_p79 | B9: Canfeda Hatun | C9: Istanbul | D9: gurre-yi Muharrem sene 1032 ila gayet-i Zilhicce sene-yi minhü | E9: 1622 | F9: 1623 | G9: Akçe | H9: certified final account | I9: 214055 | J9: 200463 | K9: 13592 | L9: 13365 | M9: 773 | N9: 12592 | O9: 0 | P9: 0 | Q9: 0 | R9: 0 | S9: 200690 | T9: 199690 | U9: 1000 | V9: 200838 | W9: 108540 | X9: 92298 | Y9: 13217 | Z9: 0 | AA9: 13217 | AB9: 13092 | AC9: 125 | AD9: 81 | AE9: 293
A10: MAD.d 1703_p76 | B10: Canfeda Hatun | C10: Istanbul | D10: gurre-yi Muharrem sene 1033 ila gayet-i Zilhicce sene-yi minhü | E10: 1623 | F10: 1624 | G10: Akçe | H10: certified final account | I10: 231547 | J10: 218455 | K10: 13092 | L10: 13217 | M10: 125 | N10: 13092 | O10: 0 | P10: 0 | Q10: 7000 | R10: 0 | S10: 211330 | T10: 211330 | U10: 0 | V10: 218350 | W10: 108600 | X10: 109750 | Y10: 13197 | Z10: 0 | AA10: 13197 | AB10: 13112 | AC10: 85 | AD10: 111 | AE10: 309
A11: MAD.d 1703_p51 | B11: Canfeda Hatun | C11: Istanbul | D11: ‘an 9 Şaban sene 1038 ila gayet-i Receb sene 1039 | E11: 1629 | F11: 1630 | G11: Akçe | H11: certified final account | I11: 233935 | J11: 198687 | K11: 35248 | L11: 34309 | M11: 0 | N11: 34309 | O11: 5692 | P11: 0 | Q11: 0 | R11: 0 | S11: 199626 | T11: 192995 | U11: 6631 | V11: 178683 | W11: 107570 | X11: 71113 | Y11: 55252 | Z11: 1480 | AA11: 53772 | AB11: 35208 | AC11: 18564 | AD11: 83 | AE11: 298
A12: MAD.d 1703_p24 | B12: Canfeda Hatun | C12: Istanbul | D12: gurre-yi Şaban sene 1044 ila 28 Şaban sene 1045 | E12: 1635 | F12: 1636 | G12: Akçe | H12: certified final account | I12: 240663 | J12: 202603 | K12: 38060 | L12: 49391 | M12: 527 | N12: 48864 | O12: 10804 | P12: 0 | Q12: 7715 | R12: 0 | S12: 184084 | T12: 184084 | U12: 0 | V12: 172208 | W12: 122340 | X12: 49868 | Y12: 68455 | Z12: 30335 | AA12: 38120 | AB12: 38060 | AC12: 60 | AD12: 97 | AE12: 339

Sheet Reconciliation
A1: Account (register) | B1: Year | C1: (1) Opening balance | D1: (2) Current-year revenues | E1: (3) Cumulative resources | F1: (4) Cumulative resources | G1: (5) Cumulative receivable | H1: (6) Expenditure | I1: (7) Balance after expenditure | J1: (8) Closing balance (balance after exp. − non-expenditure payments) | K1: (9) Closing (net of receivables) = closing − receivables | L1: (10) Deductibles: cumulative receivable = resources receivable
A2: ='Accounts (wide)'!A3 -> MAD.d 1703_p102 | B2: ='Accounts (wide)'!E3 -> 1615 | C2: ='Accounts (wide)'!L3-('Accounts (wide)'!M3+'Accounts (wide)'!N3) -> 0 | D2: ='Accounts (wide)'!S3-('Accounts (wide)'!T3+'Accounts (wide)'!U3) -> 0 | E2: ='Accounts (wide)'!I3-('Accounts (wide)'!J3+'Accounts (wide)'!K3) -> 0 | F2: ='Accounts (wide)'!I3-('Accounts (wide)'!L3+'Accounts (wide)'!P3+'Accounts (wide)'!Q3+'Accounts (wide)'!R3+'Accounts (wide)'!S3) -> 0 | G2: ='Accounts (wide)'!K3-('Accounts (wide)'!N3-'Accounts (wide)'!O3+'Accounts (wide)'!U3) -> 0 | H2: ='Accounts (wide)'!V3-('Accounts (wide)'!W3+'Accounts (wide)'!X3) -> 0 | I2: ='Accounts (wide)'!Y3-('Accounts (wide)'!I3-'Accounts (wide)'!V3) -> 0 | J2: ='Accounts (wide)'!AA3-('Accounts (wide)'!Y3-'Accounts (wide)'!Z3) -> 0 | K2: ='Accounts (wide)'!AC3-('Accounts (wide)'!AA3-'Accounts (wide)'!AB3) -> 0 | L2: ='Accounts (wide)'!AB3-'Accounts (wide)'!K3 -> 0
A3: ='Accounts (wide)'!A4 -> MAD.d 1703_p99 | B3: ='Accounts (wide)'!E4 -> 1616 | C3: ='Accounts (wide)'!L4-('Accounts (wide)'!M4+'Accounts (wide)'!N4) -> 0 | D3: ='Accounts (wide)'!S4-('Accounts (wide)'!T4+'Accounts (wide)'!U4) -> 0 | E3: ='Accounts (wide)'!I4-('Accounts (wide)'!J4+'Accounts (wide)'!K4) -> 0 | F3: ='Accounts (wide)'!I4-('Accounts (wide)'!L4+'Accounts (wide)'!P4+'Accounts (wide)'!Q4+'Accounts (wide)'!R4+'Accounts (wide)'!S4) -> 0 | G3: ='Accounts (wide)'!K4-('Accounts (wide)'!N4-'Accounts (wide)'!O4+'Accounts (wide)'!U4) -> 0 | H3: ='Accounts (wide)'!V4-('Accounts (wide)'!W4+'Accounts (wide)'!X4) -> 0 | I3: ='Accounts (wide)'!Y4-('Accounts (wide)'!I4-'Accounts (wide)'!V4) -> 0 | J3: ='Accounts (wide)'!AA4-('Accounts (wide)'!Y4-'Accounts (wide)'!Z4) -> 0 | K3: ='Accounts (wide)'!AC4-('Accounts (wide)'!AA4-'Accounts (wide)'!AB4) -> 0 | L3: ='Accounts (wide)'!AB4-'Accounts (wide)'!K4 -> 0
A4: ='Accounts (wide)'!A5 -> MAD.d 1703_p95 | B4: ='Accounts (wide)'!E5 -> 1617 | C4: ='Accounts (wide)'!L5-('Accounts (wide)'!M5+'Accounts (wide)'!N5) -> 0 | D4: ='Accounts (wide)'!S5-('Accounts (wide)'!T5+'Accounts (wide)'!U5) -> 0 | E4: ='Accounts (wide)'!I5-('Accounts (wide)'!J5+'Accounts (wide)'!K5) -> 0 | F4: ='Accounts (wide)'!I5-('Accounts (wide)'!L5+'Accounts (wide)'!P5+'Accounts (wide)'!Q5+'Accounts (wide)'!R5+'Accounts (wide)'!S5) -> 0 | G4: ='Accounts (wide)'!K5-('Accounts (wide)'!N5-'Accounts (wide)'!O5+'Accounts (wide)'!U5) -> 0 | H4: ='Accounts (wide)'!V5-('Accounts (wide)'!W5+'Accounts (wide)'!X5) -> 0 | I4: ='Accounts (wide)'!Y5-('Accounts (wide)'!I5-'Accounts (wide)'!V5) -> 0 | J4: ='Accounts (wide)'!AA5-('Accounts (wide)'!Y5-'Accounts (wide)'!Z5) -> 0 | K4: ='Accounts (wide)'!AC5-('Accounts (wide)'!AA5-'Accounts (wide)'!AB5) -> 0 | L4: ='Accounts (wide)'!AB5-'Accounts (wide)'!K5 -> 0
A5: ='Accounts (wide)'!A6 -> MAD.d 1703_p92 | B5: ='Accounts (wide)'!E6 -> 1617 | C5: ='Accounts (wide)'!L6-('Accounts (wide)'!M6+'Accounts (wide)'!N6) -> 0 | D5: ='Accounts (wide)'!S6-('Accounts (wide)'!T6+'Accounts (wide)'!U6) -> 0 | E5: ='Accounts (wide)'!I6-('Accounts (wide)'!J6+'Accounts (wide)'!K6) -> 0 | F5: ='Accounts (wide)'!I6-('Accounts (wide)'!L6+'Accounts (wide)'!P6+'Accounts (wide)'!Q6+'Accounts (wide)'!R6+'Accounts (wide)'!S6) -> 0 | G5: ='Accounts (wide)'!K6-('Accounts (wide)'!N6-'Accounts (wide)'!O6+'Accounts (wide)'!U6) -> 0 | H5: ='Accounts (wide)'!V6-('Accounts (wide)'!W6+'Accounts (wide)'!X6) -> 0 | I5: ='Accounts (wide)'!Y6-('Accounts (wide)'!I6-'Accounts (wide)'!V6) -> 0 | J5: ='Accounts (wide)'!AA6-('Accounts (wide)'!Y6-'Accounts (wide)'!Z6) -> 0 | K5: ='Accounts (wide)'!AC6-('Accounts (wide)'!AA6-'Accounts (wide)'!AB6) -> 0 | L5: ='Accounts (wide)'!AB6-'Accounts (wide)'!K6 -> 0
A6: ='Accounts (wide)'!A7 -> MAD.d 1703_p88 | B6: ='Accounts (wide)'!E7 -> 1618 | C6: ='Accounts (wide)'!L7-('Accounts (wide)'!M7+'Accounts (wide)'!N7) -> 0 | D6: ='Accounts (wide)'!S7-('Accounts (wide)'!T7+'Accounts (wide)'!U7) -> 0 | E6: ='Accounts (wide)'!I7-('Accounts (wide)'!J7+'Accounts (wide)'!K7) -> 0 | F6: ='Accounts (wide)'!I7-('Accounts (wide)'!L7+'Accounts (wide)'!P7+'Accounts (wide)'!Q7+'Accounts (wide)'!R7+'Accounts (wide)'!S7) -> 0 | G6: ='Accounts (wide)'!K7-('Accounts (wide)'!N7-'Accounts (wide)'!O7+'Accounts (wide)'!U7) -> 0 | H6: ='Accounts (wide)'!V7-('Accounts (wide)'!W7+'Accounts (wide)'!X7) -> 0 | I6: ='Accounts (wide)'!Y7-('Accounts (wide)'!I7-'Accounts (wide)'!V7) -> -4100 | J6: ='Accounts (wide)'!AA7-('Accounts (wide)'!Y7-'Accounts (wide)'!Z7) -> 0 | K6: ='Accounts (wide)'!AC7-('Accounts (wide)'!AA7-'Accounts (wide)'!AB7) -> 0 | L6: ='Accounts (wide)'!AB7-'Accounts (wide)'!K7 -> 0
A7: ='Accounts (wide)'!A8 -> MAD.d 1703_p85 | B7: ='Accounts (wide)'!E8 -> 1619 | C7: ='Accounts (wide)'!L8-('Accounts (wide)'!M8+'Accounts (wide)'!N8) -> 0 | D7: ='Accounts (wide)'!S8-('Accounts (wide)'!T8+'Accounts (wide)'!U8) -> 0 | E7: ='Accounts (wide)'!I8-('Accounts (wide)'!J8+'Accounts (wide)'!K8) -> 0 | F7: ='Accounts (wide)'!I8-('Accounts (wide)'!L8+'Accounts (wide)'!P8+'Accounts (wide)'!Q8+'Accounts (wide)'!R8+'Accounts (wide)'!S8) -> 0 | G7: ='Accounts (wide)'!K8-('Accounts (wide)'!N8-'Accounts (wide)'!O8+'Accounts (wide)'!U8) -> 0 | H7: ='Accounts (wide)'!V8-('Accounts (wide)'!W8+'Accounts (wide)'!X8) -> 0 | I7: ='Accounts (wide)'!Y8-('Accounts (wide)'!I8-'Accounts (wide)'!V8) -> 0 | J7: ='Accounts (wide)'!AA8-('Accounts (wide)'!Y8-'Accounts (wide)'!Z8) -> 0 | K7: ='Accounts (wide)'!AC8-('Accounts (wide)'!AA8-'Accounts (wide)'!AB8) -> 0 | L7: ='Accounts (wide)'!AB8-'Accounts (wide)'!K8 -> 0
A8: ='Accounts (wide)'!A9 -> MAD.d 1703_p79 | B8: ='Accounts (wide)'!E9 -> 1622 | C8: ='Accounts (wide)'!L9-('Accounts (wide)'!M9+'Accounts (wide)'!N9) -> 0 | D8: ='Accounts (wide)'!S9-('Accounts (wide)'!T9+'Accounts (wide)'!U9) -> 0 | E8: ='Accounts (wide)'!I9-('Accounts (wide)'!J9+'Accounts (wide)'!K9) -> 0 | F8: ='Accounts (wide)'!I9-('Accounts (wide)'!L9+'Accounts (wide)'!P9+'Accounts (wide)'!Q9+'Accounts (wide)'!R9+'Accounts (wide)'!S9) -> 0 | G8: ='Accounts (wide)'!K9-('Accounts (wide)'!N9-'Accounts (wide)'!O9+'Accounts (wide)'!U9) -> 0 | H8: ='Accounts (wide)'!V9-('Accounts (wide)'!W9+'Accounts (wide)'!X9) -> 0 | I8: ='Accounts (wide)'!Y9-('Accounts (wide)'!I9-'Accounts (wide)'!V9) -> 0 | J8: ='Accounts (wide)'!AA9-('Accounts (wide)'!Y9-'Accounts (wide)'!Z9) -> 0 | K8: ='Accounts (wide)'!AC9-('Accounts (wide)'!AA9-'Accounts (wide)'!AB9) -> 0 | L8: ='Accounts (wide)'!AB9-'Accounts (wide)'!K9 -> -500
A9: ='Accounts (wide)'!A10 -> MAD.d 1703_p76 | B9: ='Accounts (wide)'!E10 -> 1623 | C9: ='Accounts (wide)'!L10-('Accounts (wide)'!M10+'Accounts (wide)'!N10) -> 0 | D9: ='Accounts (wide)'!S10-('Accounts (wide)'!T10+'Accounts (wide)'!U10) -> 0 | E9: ='Accounts (wide)'!I10-('Accounts (wide)'!J10+'Accounts (wide)'!K10) -> 0 | F9: ='Accounts (wide)'!I10-('Accounts (wide)'!L10+'Accounts (wide)'!P10+'Accounts (wide)'!Q10+'Accounts (wide)'!R10+'Accounts (wide)'!S10) -> 0 | G9: ='Accounts (wide)'!K10-('Accounts (wide)'!N10-'Accounts (wide)'!O10+'Accounts (wide)'!U10) -> 0 | H9: ='Accounts (wide)'!V10-('Accounts (wide)'!W10+'Accounts (wide)'!X10) -> 0 | I9: ='Accounts (wide)'!Y10-('Accounts (wide)'!I10-'Accounts (wide)'!V10) -> 0 | J9: ='Accounts (wide)'!AA10-('Accounts (wide)'!Y10-'Accounts (wide)'!Z10) -> 0 | K9: ='Accounts (wide)'!AC10-('Accounts (wide)'!AA10-'Accounts (wide)'!AB10) -> 0 | L9: ='Accounts (wide)'!AB10-'Accounts (wide)'!K10 -> 20
A10: ='Accounts (wide)'!A11 -> MAD.d 1703_p51 | B10: ='Accounts (wide)'!E11 -> 1629 | C10: ='Accounts (wide)'!L11-('Accounts (wide)'!M11+'Accounts (wide)'!N11) -> 0 | D10: ='Accounts (wide)'!S11-('Accounts (wide)'!T11+'Accounts (wide)'!U11) -> 0 | E10: ='Accounts (wide)'!I11-('Accounts (wide)'!J11+'Accounts (wide)'!K11) -> 0 | F10: ='Accounts (wide)'!I11-('Accounts (wide)'!L11+'Accounts (wide)'!P11+'Accounts (wide)'!Q11+'Accounts (wide)'!R11+'Accounts (wide)'!S11) -> 0 | G10: ='Accounts (wide)'!K11-('Accounts (wide)'!N11-'Accounts (wide)'!O11+'Accounts (wide)'!U11) -> 0 | H10: ='Accounts (wide)'!V11-('Accounts (wide)'!W11+'Accounts (wide)'!X11) -> 0 | I10: ='Accounts (wide)'!Y11-('Accounts (wide)'!I11-'Accounts (wide)'!V11) -> 0 | J10: ='Accounts (wide)'!AA11-('Accounts (wide)'!Y11-'Accounts (wide)'!Z11) -> 0 | K10: ='Accounts (wide)'!AC11-('Accounts (wide)'!AA11-'Accounts (wide)'!AB11) -> 0 | L10: ='Accounts (wide)'!AB11-'Accounts (wide)'!K11 -> -40
A11: ='Accounts (wide)'!A12 -> MAD.d 1703_p24 | B11: ='Accounts (wide)'!E12 -> 1635 | C11: ='Accounts (wide)'!L12-('Accounts (wide)'!M12+'Accounts (wide)'!N12) -> 0 | D11: ='Accounts (wide)'!S12-('Accounts (wide)'!T12+'Accounts (wide)'!U12) -> 0 | E11: ='Accounts (wide)'!I12-('Accounts (wide)'!J12+'Accounts (wide)'!K12) -> 0 | F11: ='Accounts (wide)'!I12-('Accounts (wide)'!L12+'Accounts (wide)'!P12+'Accounts (wide)'!Q12+'Accounts (wide)'!R12+'Accounts (wide)'!S12) -> -527 | G11: ='Accounts (wide)'!K12-('Accounts (wide)'!N12-'Accounts (wide)'!O12+'Accounts (wide)'!U12) -> 0 | H11: ='Accounts (wide)'!V12-('Accounts (wide)'!W12+'Accounts (wide)'!X12) -> 0 | I11: ='Accounts (wide)'!Y12-('Accounts (wide)'!I12-'Accounts (wide)'!V12) -> 0 | J11: ='Accounts (wide)'!AA12-('Accounts (wide)'!Y12-'Accounts (wide)'!Z12) -> 0 | K11: ='Accounts (wide)'!AC12-('Accounts (wide)'!AA12-'Accounts (wide)'!AB12) -> 0 | L11: ='Accounts (wide)'!AB12-'Accounts (wide)'!K12 -> 0
A15: (1) | B15: Opening balance, total = Opening cash + Opening receivables
A16: (2) | B16: Current year revenues, total = Received + Receivables
A17: (3) | B17: Cumulative resources, total = Received + Receivables
A18: (4) | B18: Cumulative resources, total = Opening balance + Non-regular revenue + Current year revenue
A19: (5) | B19: Cumulative resources, receivable = Opening receivables - Prior receivables collected + Current year receivables
A20: (6) | B20: Expenditure, total = Salaries + Outlay and repair
A21: (7) | B21: Balance after expenditure = Cumulative revenues, total - Expenditure, total
A22: (8) | B22: Closing balance = Balance after expenditure - Non-expenditure payments
A23: (9) | B23: Closing balance net of receivables = Closing - Deductibles
A24: (10) | B24: Deductibles = Cumulative receivables

Sheet Data dictionary
A1: Code | B1: Flow block | C1: Ottoman header | D1: English label | E1: Identity / note
A2: L1 | B2: Cumulative resources | C2: Asl-ı mâl | D2: Cumulative resources, total | E2: L1= L2 + L3.1 + L3.2 + L3.3 + L4; =L1A + L1B
A3: L1A | B3: Cumulative resources | C3: Asl-ı mâl makbûz | D3: Cumulative resources received | E3: L1A = L2A + L3.1 + L3.2 + L3.3 + L2T + L4A
A4: L1B | B4: Cumulative resources | C4: Asl-ı mâl bâkî | D4: Cumulative resources receivable | E4: L1B = L2B + L4B − L2T, also = L9
A5: L2 | B5: Opening balance | C5: Bâkiye-i muhâsebe-i sene-i mâziyye | D5: Opening balance, total | E5: L2 = L2A + L2B
A6: L2A | B6: Opening balance | C6: Bâkiye der kise | D6: Opening cash on hand | E6: carried from prior year L10
A7: L2B | B7: Opening balance | C7: Bâkiye der zimem | D7: Opening receivables
A8: L2T | B8: Opening balance | C8: Tahsîl | D8: Collection of a prior-year receivable
A9: L3.1 | B9: Non-regular revenues | C9: İstikrâz | D9: Loan taken in
A10: L3.2 | B10: Non-regular revenues | C10: Akçe-yi pîşîn | D10: Advance payment received from tax-farmers
A11: L3.3 | B11: Non-regular revenues | C11: murabehe-yi nükud-ı vakıf; an akçe-yi ava'id-i mütevelli; akçe-yi imdadiye, etc. | D11: Other non-regular inflow
A12: L4 | B12: Current-year revenues | C12: Mahsûlât | D12: Current year revenue, total | E12: L4 = L4A + L4B
A13: L4A | B13: Current-year revenues | C13: Mahsûlât makbûz | D13: Current year revenue received
A14: L4B | B14: Current-year revenues | C14: Mahsûlât bâkî | D14: Current year revenue receivable
A15: L5 | B15: Expenditures | C15: Vuzi‘a min zâlik | D15: Expenditure, total | E15: L5 = L5A + L5B
A16: L5A | B16: Expenditures | C16: El-vezâif | D16: Stipends & salaries
A17: L5B | B17: Expenditures | C17: El-ihrâcât ma‘a meremmet | D17: Outlays & repairs
A18: L6 | B18: Balance | C18: El-bâkî | D18: Balance after expenditures | E18: L6 = L1 − L5
A19: L7 | B19: Deductible | C19: Min zâlike’l-bâkî | D19: Non-expenditure payments
A20: L8 | B20: Balance | C20: Sahhü’l-bâkî | D20: Closing balance | E20: L8 = L6 − L7, carries to next-year L2
A21: L9 | B21: Deductible | C21: Minhâ | D21: Cumulative receivable | E21: =L1B
A22: L10 | B22: Balance | C22: Nassü’l-bâkî | D22: Closing balance net of receivables | E22: L10 = L8 − L9, carries to next-year L2A
A23: L11 | B23: Payroll data | C23: Nefer | D23: Headcount (employees) | E23: memo line
A24: L12 | B24: Payroll data | C24: Yevmiyye | D24: Daily wage total | E24: memo line
